stempl_webpy/__init__.py
stempl_webpy-1.0.2.dist-info/LICENSE
stempl_webpy-1.0.2.dist-info/METADATA
stempl_webpy-1.0.2.dist-info/WHEEL
stempl_webpy-1.0.2.dist-info/top_level.txt
stempl_webpy-1.0.2.dist-info/RECORD
