Metadata-Version: 2.1
Name: stempl-webpy
Version: 1.0.2
Summary: A WebPy-Framework project template for serpent-cli
Author-email: Carl Furtado <carlzfurtado@gmail.com>
License: The MIT License (MIT)
Project-URL: Home, https://github.com/User0332/serpent/templatespack/webpy
Classifier: License :: OSI Approved :: MIT License
License-File: LICENSE
Requires-Dist: webpy-framework
